Metadata-Version: 2.1
Name: PlotLinearAlgebra
Version: 1.9.0
Summary: Herramientas para la visualización de vectores bidimensionales y tridimensionales
Home-page: https://github.com/josorio398
Author: Jhonny Osorio Gallego
Author-email: osoriojohnny1986@gmail.com
License: Creative Commons Attribution-NonCommercial-NoDerivs 3.0 Unported (CC BY-NC-ND 3.0)
Download-URL: https://github.com/josorio398/ALGEBRA-LINEAL-CON-PYTHON/blob/master/plotvectors.py
Keywords: LinearAlgebra,Linearalgebra,plotvectors,plotvector,vectorplot,vectorsplot,algebralineal,plot
Platform: UNKNOWN
Classifier: Development Status :: 4 - Beta
Classifier: Intended Audience :: Developers
Classifier: Topic :: Software Development :: Build Tools
Classifier: Programming Language :: Python :: 3.4
Classifier: Programming Language :: Python :: 3.5
Classifier: Programming Language :: Python :: 3.6
Classifier: Programming Language :: Python :: 3.7
Classifier: Programming Language :: Python :: 3.8
Classifier: Programming Language :: Python :: 3.9
License-File: LICENSE.txt
